{
    "exp": 1602735212,
    "iat": 1602734312,
    "auth_time": 1602731339,
    "jti": "######-####-####",
    "iss": "https://login.dsop.io/auth/realms/baby-yoda",
    "sub": "######-####-####",
    "typ": "Bearer",
    "azp": "platform1_a8604cc9-f5e9-4656-802d-d05624370245_hello-world-authservice",
    "nonce": "###################",
    "session_state": "######-####-####",
    "acr": "0",
    "scope": "#### ######",
    "group-simple": [
        "#########",
        "#######",
        "####"
    ],
    "preferred_username": "real-dba-snuffy",
    "given_name": "John",
    "activecac": "",
    "affiliation": "US Air Force",
    "group-full": [
        "##########/########/#########",
        "##########/########/#######",
        "##########/########/####"
    ],
    "organization": "Platform One",
    "name": "John Snuffy",
    "nickname": "The Snuffmaster",
    "usercertificate": "##################",
    "rank": "SrA",
    "position": "Software Developer",
    "family_name": "Snuffy",
    "email": "john.snuffy@fakename.com"
}